djangoldp_joboffer/__init__.py
djangoldp_joboffer/admin.py
djangoldp_joboffer/apps.py
djangoldp_joboffer/djangoldp_urls.py
djangoldp_joboffer/factories.py
djangoldp_joboffer/models.py
djangoldp_joboffer/notifications.py
djangoldp_joboffer/serializers.py
djangoldp_joboffer/settings.py
djangoldp_joboffer/views.py
djangoldp_joboffer/management/__init__.py
djangoldp_joboffer/management/commands/__init__.py
djangoldp_joboffer/management/commands/mock_joboffer.py
djangoldp_joboffer/migrations/0001_initial.py
djangoldp_joboffer/migrations/0002_joboffer_urlid.py
djangoldp_joboffer/migrations/0003_auto_20200522_1521.py
djangoldp_joboffer/migrations/0004_auto_20200610_1323.py
djangoldp_joboffer/migrations/0005_auto_20200619_0815.py
djangoldp_joboffer/migrations/0006_auto_20200804_1803.py
djangoldp_joboffer/migrations/0007_auto_20200924_1937.py
djangoldp_joboffer/migrations/0008_auto_20210326_1424.py
djangoldp_joboffer/migrations/0009_auto_20210531_1311.py
djangoldp_joboffer/migrations/0010_joboffer_location.py
djangoldp_joboffer/migrations/0011_joboffer_community_alter_joboffer_urlid.py
djangoldp_joboffer/migrations/0012_auto_20231016_1908.py
djangoldp_joboffer/migrations/0013_add_timestamps_to_models.py
djangoldp_joboffer/migrations/__init__.py
djangoldp_joboffer/templates/__init__.py
djangoldp_joboffer/templates/joboffer/email.html
djangoldp_joboffer/tests/__init__.py
djangoldp_joboffer/tests/runner.py
djangoldp_joboffer/tests/tests_inbox.py
djangoldp_joboffer/tests/tests_notifications.py
djangoldp_joboffer/tests/tests_post.py
djangoldp_joboffer-5.0.0.dist-info/METADATA
djangoldp_joboffer-5.0.0.dist-info/WHEEL
djangoldp_joboffer-5.0.0.dist-info/top_level.txt
djangoldp_joboffer-5.0.0.dist-info/RECORD
