Metadata-Version: 2.4
Name: djangoldp_joboffer
Version: 5.0.0
Summary: djangoldp package for job offer data models
Home-page: https://git.startinblox.com/djangoldp-packages/djangoldp-joboffer
Author: Startin'blox
Author-email: jbaptiste@startinblox.com
License: MIT
Requires-Dist: djangoldp~=5.0.0
Requires-Dist: djangoldp_skill~=5.0.0
Requires-Dist: djangoldp_account~=5.0.0
Requires-Dist: djangoldp_notification~=5.0.0
Provides-Extra: dev
Requires-Dist: factory_boy>=2.11.0; extra == "dev"
Requires-Dist: djangoldp_conversation; extra == "dev"
Requires-Dist: djangoldp_i18n; extra == "dev"
